bromine/__init__.py
bromine/_version.py
bromine/exceptions.py
bromine/application/__init__.py
bromine/application/application.py
bromine/element/__init__.py
bromine/element/base.py
bromine/element/layout.py
bromine/element/locator.py
bromine/element/screenshots.py
bromine/element/scroll.py
bromine/element/size.py
bromine/element/web_element.py
bromine/page/__init__.py
bromine/page/current_url_test.py
bromine/page/layout.py
bromine/page/page.py
bromine/page/screenshots.py
bromine/page/scroll.py
bromine/page/size.py
bromine/utils/__init__.py
bromine/utils/geometry.py
bromine/utils/image.py
bromine/utils/robots_txt.py
bromine/utils/url.py
bromine/utils/wait.py
bromine/webdriver/__init__.py
bromine/webdriver/webdriver.py
bromine/webdriver/window.py
bromine-0.4.0.dist-info/LICENSE.txt
bromine-0.4.0.dist-info/METADATA
bromine-0.4.0.dist-info/WHEEL
bromine-0.4.0.dist-info/top_level.txt
bromine-0.4.0.dist-info/RECORD
