Metadata-Version: 2.1
Name: bromine
Version: 0.4.0
Summary: A high-level web testing library based on Selenium and PageObject Pattern
Home-page: https://github.com/Etiqa/bromine
Author: Etiqa s.r.l.
Author-email: 
License: 2-clause BSD License
Platform: UNKNOWN
Classifier: Development Status :: 2 - Pre-Alpha
Classifier: Intended Audience :: Developers
Classifier: Topic :: Software Development :: Quality Assurance
Classifier: Topic :: Software Development :: Testing
Classifier: Topic :: Software Development :: Libraries
Classifier: License :: OSI Approved :: BSD License
Classifier: Programming Language :: Python :: 3
Classifier: Programming Language :: Python :: 3.6
Classifier: Programming Language :: Python :: 3.7
Classifier: Programming Language :: Python :: 3.8
Requires-Python: >=3.6, <4
Requires-Dist: Pillow
Requires-Dist: PyHamcrest
Requires-Dist: requests
Requires-Dist: selenium
Requires-Dist: six
